permit_datafilter/__init__.py
permit_datafilter/boolean_expression/__init__.py
permit_datafilter/boolean_expression/schemas.py
permit_datafilter/boolean_expression/translator.py
permit_datafilter/compile_api/__init__.py
permit_datafilter/compile_api/compile_client.py
permit_datafilter/compile_api/schemas.py
permit_datafilter/plugins/__init__.py
permit_datafilter/plugins/sqlalchemy.py
permit_datafilter/rego_ast/__init__.py
permit_datafilter/rego_ast/parser.py
tests/__init__.py
tests/test_ast_parser.py
tests/test_ast_translation.py
tests/test_boolean_expression_schema.py
tests/test_compile_parsing.py
tests/test_data_filtering_usage.py
permit_datafilter-0.0.3.dist-info/METADATA
permit_datafilter-0.0.3.dist-info/WHEEL
permit_datafilter-0.0.3.dist-info/top_level.txt
permit_datafilter-0.0.3.dist-info/RECORD
